{"trial_id": "c8b662da56b216a618fddd275d05c7d0", "hyperparameters": {"space": [{"class_name": "Choice", "config": {"name": "activation", "default": "relu", "conditions": [], "values": ["relu", "tanh", "sigmoid"], "ordered": false}}, {"class_name": "Int", "config": {"name": "first_units", "default": null, "conditions": [], "min_value": 1, "max_value": 80, "step": 2, "sampling": null}}, {"class_name": "Int", "config": {"name": "num_layers", "default": null, "conditions": [], "min_value": 1, "max_value": 6, "step": 1, "sampling": null}}, {"class_name": "Int", "config": {"name": "units_0", "default": null, "conditions": [], "min_value": 1, "max_value": 80, "step": 2, "sampling": null}}, {"class_name": "Int", "config": {"name": "units_1", "default": null, "conditions": [], "min_value": 1, "max_value": 80, "step": 2, "sampling": null}}, {"class_name": "Int", "config": {"name": "units_2", "default": null, "conditions": [], "min_value": 1, "max_value": 80, "step": 2, "sampling": null}}, {"class_name": "Int", "config": {"name": "units_3", "default": null, "conditions": [], "min_value": 1, "max_value": 80, "step": 2, "sampling": null}}, {"class_name": "Int", "config": {"name": "units_4", "default": null, "conditions": [], "min_value": 1, "max_value": 80, "step": 2, "sampling": null}}, {"class_name": "Int", "config": {"name": "units_5", "default": null, "conditions": [], "min_value": 1, "max_value": 80, "step": 2, "sampling": null}}], "values": {"activation": "relu", "first_units": 3, "num_layers": 4, "units_0": 39, "units_1": 69, "units_2": 31, "units_3": 43, "units_4": 43, "units_5": 9, "tuner/epochs": 200, "tuner/initial_epoch": 0, "tuner/bracket": 0, "tuner/round": 0}}, "metrics": {"metrics": {"loss": {"direction": "min", "observations": [{"value": [0.6218812465667725], "step": 0}]}, "accuracy": {"direction": "max", "observations": [{"value": [0.7329730987548828], "step": 0}]}, "val_loss": {"direction": "min", "observations": [{"value": [0.5830912590026855], "step": 0}]}, "val_accuracy": {"direction": "max", "observations": [{"value": [0.7327113747596741], "step": 0}]}}}, "score": 0.7327113747596741, "best_step": 0, "status": "COMPLETED"}